wizlib/__init__.py
wizlib/app.py
wizlib/class_family.py
wizlib/command.py
wizlib/config_handler.py
wizlib/error.py
wizlib/handler.py
wizlib/io.py
wizlib/parser.py
wizlib/stream_handler.py
wizlib/super_wrapper.py
wizlib/test_case.py
wizlib/ui/__init__.py
wizlib/ui/shell/__init__.py
wizlib/ui/shell/line_editor.py
wizlib/ui/shell_ui.py
wizlib/ui/text_wrapper.py
wizlib/ui_handler.py
wizlib-3.4.0.dist-info/METADATA
wizlib-3.4.0.dist-info/WHEEL
wizlib-3.4.0.dist-info/RECORD
