Metadata-Version: 2.4
Name: wizlib
Version: 3.4.0
Summary: Framework for flexible and powerful command-line applications
License: MIT
Author: Steampunk Wizard
Author-email: wizlib@steampunkwizard.ca
Requires-Python: >=3.11,<4.0
Classifier: License :: OSI Approved :: MIT License
Classifier: Programming Language :: Python :: 3
Classifier: Programming Language :: Python :: 3.11
Classifier: Programming Language :: Python :: 3.12
Classifier: Programming Language :: Python :: 3.13
Classifier: Programming Language :: Python :: 3.14
Requires-Dist: PyYAML (>=6.0.1,<7.0.0)
Requires-Dist: readchar (>=4.0.5,<5.0.0)
